leanit_mweb/__init__.py
leanit_mweb/auth.py
leanit_mweb/form.py
leanit_mweb/manage.py
leanit_mweb/staticfiles.py
leanit_mweb/testutils.py
leanit_mweb/thread.py
leanit_mweb/utils.py
leanit_mweb/yuga.py
leanit_mweb/jinja_template/__init__.py
leanit_mweb/jinja_template/loaders.py
leanit_mweb/messaging/__init__.py
leanit_mweb/messaging/base.py
leanit_mweb/orm/__init__.py
leanit_mweb/orm/exception.py
leanit_mweb/orm/fields.py
leanit_mweb/orm/model.py
leanit_mweb/orm/password.py
leanit_mweb/orm/fields/__init__.py
leanit_mweb/orm/fields/snowflake.py
leanit_mweb/tests/__init__.py
leanit_mweb/tests/test_testutils.py
leanit_mweb/tests/orm/__init__.py
leanit_mweb/tests/orm/fields/__init__.py
leanit_mweb/tests/orm/fields/test_StringField.py
leanit_mweb/tests/orm/model/__init__.py
leanit_mweb/tests/orm/model/test_delete_all.py
leanit_mweb/views/__init__.py
leanit_mweb/views/auth.py
mweb/__init__.py
mweb/form.py
mweb/manage.py
mweb/staticfiles.py
mweb/testutils.py
mweb/thread.py
mweb/version.py
mweb/yuga.py
mweb/auth/__init__.py
mweb/auth/sso/__init__.py
mweb/auth/sso/base.py
mweb/auth/sso/microsoft/__init__.py
mweb/jinja_template/__init__.py
mweb/jinja_template/loaders.py
mweb/messaging/__init__.py
mweb/messaging/base.py
mweb/orm/__init__.py
mweb/orm/exception.py
mweb/orm/model.py
mweb/orm/password.py
mweb/orm/fields/__init__.py
mweb/orm/fields/snowflake.py
mweb/security/__init__.py
mweb/security/jwt.py
mweb/state/__init__.py
mweb/state/client.py
mweb/utils/__init__.py
mweb/utils/log.py
mweb/utils/log_catcher.py
mweb/utils/id/__init__.py
mweb/utils/id/snowflakeid.py
mweb/views/__init__.py
mweb/views/auth.py
mweb/views/dependencies.py
mweb/views/model.py
tests/__init__.py
tests/auth/__init__.py
tests/auth/sso/__init__.py
tests/auth/sso/microsoft/__init__.py
tests/auth/sso/microsoft/test_auth_callback.py
tests/auth/sso/microsoft/test_build_auth_url.py
tests/auth/sso/microsoft/test_code.py
tests/orm/__init__.py
tests/orm/fields/__init__.py
tests/orm/fields/test_StringField.py
leanit_mweb-23.7.4.dist-info/LICENSE
leanit_mweb-23.7.4.dist-info/METADATA
leanit_mweb-23.7.4.dist-info/WHEEL
leanit_mweb-23.7.4.dist-info/top_level.txt
leanit_mweb-23.7.4.dist-info/RECORD
