Metadata-Version: 2.1
Name: leanit-mweb
Version: 23.7.4
Summary: Web framework
Author: Martin Klapproth
Author-email: martin.klapproth@staxnet.de
Keywords: python,web
Classifier: Development Status :: 1 - Planning
Classifier: Intended Audience :: Developers
Classifier: Programming Language :: Python :: 3
Classifier: Operating System :: Unix
Classifier: Operating System :: MacOS :: MacOS X
Classifier: Operating System :: Microsoft :: Windows
License-File: LICENSE
Requires-Dist: fastapi (~=0.95)
Requires-Dist: uvicorn (~=0.22)
Requires-Dist: jinja2 (~=3.1)
Requires-Dist: python-multipart (~=0.0)
Requires-Dist: wtforms (~=3.0)
Requires-Dist: email-validator (~=2.0)
Requires-Dist: multidict (~=6.0)
Requires-Dist: PyYAML (~=6.0)
Requires-Dist: python-ulid (~=1.1)
Requires-Dist: snowflake-id (~=0.0)
Requires-Dist: aiohttp (~=3.7)
Requires-Dist: aioresponses (~=0.7)
Requires-Dist: bcrypt (~=4.0)
Requires-Dist: passlib (~=1.7)
Requires-Dist: python-jose[cryptography] (~=3.3)
Requires-Dist: opentelemetry-api (~=1.18)
Requires-Dist: opentelemetry-sdk (~=1.18)
Requires-Dist: opentelemetry-instrumentation-aiohttp-client (~=0.39b0)
Requires-Dist: opentelemetry-instrumentation-fastapi (~=0.39b0)
Requires-Dist: opentelemetry-instrumentation-logging (~=0.39b0)
Requires-Dist: opentelemetry-exporter-otlp (~=1.18)
Requires-Dist: sentry-sdk[fastapi] (~=1.25)
Requires-Dist: pytest
Requires-Dist: httpx
Requires-Dist: uvloop (~=0.17)
Provides-Extra: psql
Requires-Dist: psycopg2 (~=2.9) ; extra == 'psql'
Provides-Extra: ysql
Requires-Dist: psycopg2-yugabytedb (~=2.9) ; extra == 'ysql'
